[
  {
    "id": "volkswagen",
    "merke": "volkswagen",
    "navn": "Volkswagen Golf-Serie 1,0",
    "sub": "2021–2021 · eTSI 110hk Life",
    "score": 65,
    "flipScore": 72,
    "snittPris": 229532,
    "minPris": 229532,
    "maxPris": 229532,
    "snittDager": 22,
    "antallAnnonser": 1,
    "prisEndring": 22699,
    "prisData": [
      212743,
      232060,
      232060,
      235442,
      235442,
      235442
    ],
    "volum": [
      1,
      1,
      1,
      1,
      1,
      1,
      1,
      1,
      1,
      1,
      1,
      1
    ],
    "tags": [
      {
        "t": "God margin",
        "c": "g"
      },
      {
        "t": "Lavt volum",
        "c": "a"
      },
      {
        "t": "Pris opp",
        "c": "a"
      },
      {
        "t": "Under bucket",
        "c": "g"
      },
      {
        "t": "Sterk medianmargin",
        "c": "g"
      },
      {
        "t": "Mange under p25",
        "c": "g"
      }
    ],
    "ai": "Golf eTSI fra privat til 233k. Tilsvarende hos forhandler koster 250-260k. Moderat margin mulig. Lav km (63k) og 2021-modell. Ingen kjente feil.",
    "avgBucketMedianPrivate": 284532,
    "avgBucketMedianDealer": 299000,
    "avgBucketP25Private": 284532,
    "avgBucketP75Private": 284532,
    "avgLowballTarget": 213465,
    "avgLowballMargin": 71067,
    "avgMedianMargin": 55000,
    "avgCompCount": 6,
    "avgCompSpreadPct": 8,
    "bucketCoverage": 1,
    "bucketDealerCoverage": 1,
    "priceToBucketPct": 81,
    "underBucketShare": 100,
    "p25DealShare": 100,
    "topCompConfidence": "high",
    "confidenceBreakdown": {
      "high": 1
    },
    "primaryValuationSource": "bucket_private_min",
    "valuationBreakdown": {
      "bucket_private_min": 1
    },
    "sellerMix": {
      "unknown": 1
    },
    "analysisBaseCount": 1,
    "cohortFilteredCount": 1,
    "bestDealScore": 72,
    "bestMargin": 44455,
    "faktorer": [
      {
        "l": "Etterspørsel",
        "v": 70,
        "c": "#3d9960"
      },
      {
        "l": "Prismargin",
        "v": 97,
        "c": "#3d9960"
      },
      {
        "l": "Likviditet",
        "v": 15,
        "c": "#e8a020"
      },
      {
        "l": "Batteririsiko",
        "v": 60,
        "c": "#3d9960"
      }
    ]
  },
  {
    "id": "volkswagen",
    "merke": "volkswagen",
    "navn": "Volkswagen ID.4 Pure-343km-Carplay-DAB-Garanti",
    "sub": "2021–2021 · Diverse",
    "score": 88,
    "flipScore": 68,
    "snittPris": 214434,
    "minPris": 214434,
    "maxPris": 214434,
    "snittDager": 14,
    "antallAnnonser": 1,
    "prisEndring": -4566,
    "prisData": [
      219000,
      214434,
      214434
    ],
    "volum": [
      1,
      1,
      1,
      1,
      1,
      1,
      1,
      1,
      1,
      1,
      1,
      1
    ],
    "tags": [
      {
        "t": "God margin",
        "c": "g"
      },
      {
        "t": "Lavt volum",
        "c": "a"
      },
      {
        "t": "Høy score",
        "c": "g"
      },
      {
        "t": "Under bucket",
        "c": "g"
      },
      {
        "t": "Sterk medianmargin",
        "c": "g"
      },
      {
        "t": "Mange under p25",
        "c": "g"
      }
    ],
    "ai": "2021 ID.4 Pure med 47 000 km, privat selger til 219 000 kr. Dette er en svært god pris. Tilsvarende biler hos forhandler koster 250-260k. Ingen kjente feil, nye bremser. Størst gevinstpotensial i listen.",
    "avgBucketMedianPrivate": 304532,
    "avgBucketMedianDealer": 292091,
    "avgBucketP25Private": 304532,
    "avgBucketP75Private": 304532,
    "avgLowballTarget": 201568,
    "avgLowballMargin": 102964,
    "avgMedianMargin": 90098,
    "avgCompCount": 2,
    "avgCompSpreadPct": 34,
    "bucketCoverage": 1,
    "bucketDealerCoverage": 1,
    "priceToBucketPct": 70,
    "underBucketShare": 100,
    "p25DealShare": 100,
    "topCompConfidence": "low",
    "confidenceBreakdown": {
      "low": 1
    },
    "primaryValuationSource": "bucket_dealer_min",
    "valuationBreakdown": {
      "bucket_dealer_min": 1
    },
    "sellerMix": {
      "private_likely": 1
    },
    "analysisBaseCount": 1,
    "cohortFilteredCount": 0,
    "bestDealScore": 68,
    "bestMargin": 67112,
    "faktorer": [
      {
        "l": "Etterspørsel",
        "v": 93,
        "c": "#3d9960"
      },
      {
        "l": "Prismargin",
        "v": 100,
        "c": "#3d9960"
      },
      {
        "l": "Likviditet",
        "v": 15,
        "c": "#e8a020"
      },
      {
        "l": "Batteririsiko",
        "v": 60,
        "c": "#3d9960"
      }
    ]
  },
  {
    "id": "nissanleaf",
    "merke": "nissan",
    "navn": "Nissan Leaf 2017",
    "sub": "2017–2017 · ∙ 29 471 km ∙ El ∙ 175 km rekkevidde",
    "score": 0,
    "flipScore": 66,
    "snittPris": 99032,
    "minPris": 99032,
    "maxPris": 99032,
    "snittDager": 29,
    "antallAnnonser": 1,
    "prisEndring": 0,
    "prisData": [
      99032,
      99032,
      99032,
      99032,
      99032,
      99032
    ],
    "volum": [
      1,
      1,
      1,
      1,
      1,
      1,
      1,
      1,
      1,
      1,
      1,
      1
    ],
    "tags": [
      {
        "t": "Lavt volum",
        "c": "a"
      },
      {
        "t": "Under bucket",
        "c": "g"
      },
      {
        "t": "Sterk medianmargin",
        "c": "g"
      },
      {
        "t": "Mange under p25",
        "c": "g"
      }
    ],
    "ai": "Nissan Leaf 2017 — 1 annonser funnet.",
    "avgBucketMedianPrivate": 135000,
    "avgBucketMedianDealer": 149000,
    "avgBucketP25Private": 134531,
    "avgBucketP75Private": 149532,
    "avgLowballTarget": 92100,
    "avgLowballMargin": 42900,
    "avgMedianMargin": 35968,
    "avgCompCount": 5,
    "avgCompSpreadPct": 11,
    "bucketCoverage": 1,
    "bucketDealerCoverage": 1,
    "priceToBucketPct": 73,
    "underBucketShare": 100,
    "p25DealShare": 100,
    "topCompConfidence": "high",
    "confidenceBreakdown": {
      "high": 1
    },
    "primaryValuationSource": "comps_dealer_min",
    "valuationBreakdown": {
      "comps_dealer_min": 1
    },
    "sellerMix": {
      "private_likely": 1
    },
    "analysisBaseCount": 1,
    "cohortFilteredCount": 0,
    "bestDealScore": 66,
    "bestMargin": 12335,
    "faktorer": [
      {
        "l": "Etterspørsel",
        "v": 5,
        "c": "#e8a020"
      },
      {
        "l": "Prismargin",
        "v": 62,
        "c": "#3d9960"
      },
      {
        "l": "Likviditet",
        "v": 15,
        "c": "#e8a020"
      },
      {
        "l": "Batteririsiko",
        "v": 28,
        "c": "#e8a020"
      }
    ]
  },
  {
    "id": "volkswagen",
    "merke": "volkswagen",
    "navn": "Volkswagen Golf-Serie 2018",
    "sub": "2018–2018 · ∙ 69 322 km ∙ El ∙ 300 km rekkevidde",
    "score": 70,
    "flipScore": 65,
    "snittPris": 119532,
    "minPris": 119532,
    "maxPris": 119532,
    "snittDager": 22,
    "antallAnnonser": 1,
    "prisEndring": -7372,
    "prisData": [
      138021,
      143399,
      140899,
      140899,
      123282,
      139000,
      130649
    ],
    "volum": [
      1,
      1,
      1,
      1,
      1,
      1,
      1,
      1,
      1,
      1,
      1,
      1
    ],
    "tags": [
      {
        "t": "God margin",
        "c": "g"
      },
      {
        "t": "Lavt volum",
        "c": "a"
      },
      {
        "t": "Pris ned",
        "c": "g"
      },
      {
        "t": "Under bucket",
        "c": "g"
      },
      {
        "t": "Sterk medianmargin",
        "c": "g"
      },
      {
        "t": "Mange under p25",
        "c": "g"
      }
    ],
    "ai": "Privat selger av e-Golf til 119 532 kr med 69k km. Har rust ved hjulbue og liten bulk - dette må vurderes nøye. Prisen er god for en 2019-modell, men reparasjon kan spise margin.",
    "avgBucketMedianPrivate": 159532,
    "avgBucketMedianDealer": 139000,
    "avgBucketP25Private": 159532,
    "avgBucketP75Private": 159532,
    "avgLowballTarget": 111165,
    "avgLowballMargin": 48367,
    "avgMedianMargin": 40000,
    "avgCompCount": 2,
    "avgCompSpreadPct": 19,
    "bucketCoverage": 1,
    "bucketDealerCoverage": 1,
    "priceToBucketPct": 75,
    "underBucketShare": 100,
    "p25DealShare": 100,
    "topCompConfidence": "low",
    "confidenceBreakdown": {
      "low": 1
    },
    "primaryValuationSource": "bucket_private",
    "valuationBreakdown": {
      "bucket_private": 1
    },
    "sellerMix": {
      "private_likely": 1
    },
    "analysisBaseCount": 1,
    "cohortFilteredCount": 0,
    "bestDealScore": 65,
    "bestMargin": 32455,
    "faktorer": [
      {
        "l": "Etterspørsel",
        "v": 75,
        "c": "#3d9960"
      },
      {
        "l": "Prismargin",
        "v": 100,
        "c": "#3d9960"
      },
      {
        "l": "Likviditet",
        "v": 15,
        "c": "#e8a020"
      },
      {
        "l": "Batteririsiko",
        "v": 36,
        "c": "#e8a020"
      }
    ]
  },
  {
    "id": "hyundaiion",
    "merke": "hyundai",
    "navn": "Hyundai Ioniq 5",
    "sub": "2022–2025 · AWD Premium",
    "score": 68,
    "flipScore": 63,
    "snittPris": 326766,
    "minPris": 254532,
    "maxPris": 399000,
    "snittDager": 23,
    "antallAnnonser": 2,
    "prisEndring": 13428,
    "prisData": [
      365702,
      366897,
      365879,
      365808,
      379206,
      369920,
      379130
    ],
    "volum": [
      2,
      2,
      2,
      2,
      2,
      2,
      2,
      2,
      2,
      2,
      2,
      2
    ],
    "tags": [
      {
        "t": "Lavt volum",
        "c": "a"
      },
      {
        "t": "Pris opp",
        "c": "a"
      },
      {
        "t": "Under bucket",
        "c": "g"
      },
      {
        "t": "Sterk medianmargin",
        "c": "g"
      },
      {
        "t": "Mange under p25",
        "c": "g"
      }
    ],
    "ai": "Hyundai Ioniq 5 AWD 2022 med 78k km til 254 532 kr. Bakfanger byttet etter skade. Prisen er OK, men skadehistorikk reduserer verdi. Markedsverdi rundt 270k.",
    "avgBucketMedianPrivate": 368016,
    "avgBucketMedianDealer": 379450,
    "avgBucketP25Private": 352325,
    "avgBucketP75Private": 380826,
    "avgLowballTarget": 305165,
    "avgLowballMargin": 62851,
    "avgMedianMargin": 41250,
    "avgCompCount": 13,
    "avgCompSpreadPct": 12,
    "bucketCoverage": 2,
    "bucketDealerCoverage": 2,
    "priceToBucketPct": 89,
    "underBucketShare": 100,
    "p25DealShare": 100,
    "topCompConfidence": "high",
    "confidenceBreakdown": {
      "high": 1,
      "low": 1
    },
    "primaryValuationSource": "comps_private_thin_min",
    "valuationBreakdown": {
      "comps_private_thin_min": 1,
      "bucket_private_min": 1
    },
    "sellerMix": {
      "unknown": 1,
      "private_likely": 1
    },
    "analysisBaseCount": 2,
    "cohortFilteredCount": 0,
    "bestDealScore": 65,
    "bestMargin": 26435,
    "faktorer": [
      {
        "l": "Etterspørsel",
        "v": 73,
        "c": "#3d9960"
      },
      {
        "l": "Prismargin",
        "v": 38,
        "c": "#e8a020"
      },
      {
        "l": "Likviditet",
        "v": 30,
        "c": "#e8a020"
      },
      {
        "l": "Batteririsiko",
        "v": 84,
        "c": "#3d9960"
      }
    ]
  },
  {
    "id": "toyotarav4",
    "merke": "toyota",
    "navn": "Toyota RAV4 Plug-in",
    "sub": "2020–2021 · AWD",
    "score": 83,
    "flipScore": 61,
    "snittPris": 416766,
    "minPris": 414000,
    "maxPris": 419532,
    "snittDager": 21,
    "antallAnnonser": 2,
    "prisEndring": -6662,
    "prisData": [
      514197,
      513303,
      512928,
      512731,
      506423,
      484604,
      507535
    ],
    "volum": [
      2,
      2,
      2,
      2,
      2,
      2,
      2,
      2,
      2,
      2,
      2,
      2
    ],
    "tags": [
      {
        "t": "Lavt volum",
        "c": "a"
      },
      {
        "t": "Høy score",
        "c": "g"
      },
      {
        "t": "Pris ned",
        "c": "g"
      },
      {
        "t": "Under bucket",
        "c": "g"
      },
      {
        "t": "Sterk medianmargin",
        "c": "g"
      },
      {
        "t": "Mange under p25",
        "c": "g"
      }
    ],
    "ai": "Toyota RAV4 PHEV Executive 2020 med 61 500 km til 424 900 kr. Privat selger (Høvik). Dette er toppmodell med alt utstyr. Prisen er GOD under markedsverdi for en Executive med lav km. RAV4 PHEV er svært etterspurt. Høy margin mulig.",
    "avgBucketMedianPrivate": 465000,
    "avgBucketMedianDealer": 435250,
    "avgBucketP25Private": 446766,
    "avgBucketP75Private": 482450,
    "avgLowballTarget": 389690,
    "avgLowballMargin": 75310,
    "avgMedianMargin": 48234,
    "avgCompCount": 25,
    "avgCompSpreadPct": 9,
    "bucketCoverage": 2,
    "bucketDealerCoverage": 2,
    "priceToBucketPct": 90,
    "underBucketShare": 100,
    "p25DealShare": 100,
    "topCompConfidence": "high",
    "confidenceBreakdown": {
      "high": 2
    },
    "primaryValuationSource": "comps_dealer_min",
    "valuationBreakdown": {
      "comps_dealer_min": 2
    },
    "sellerMix": {
      "private_likely": 1,
      "unknown": 1
    },
    "analysisBaseCount": 2,
    "cohortFilteredCount": 2,
    "bestDealScore": 76,
    "bestMargin": 8566,
    "faktorer": [
      {
        "l": "Etterspørsel",
        "v": 88,
        "c": "#3d9960"
      },
      {
        "l": "Prismargin",
        "v": 8,
        "c": "#e8a020"
      },
      {
        "l": "Likviditet",
        "v": 30,
        "c": "#e8a020"
      },
      {
        "l": "Batteririsiko",
        "v": 60,
        "c": "#3d9960"
      }
    ]
  },
  {
    "id": "volkswagen",
    "merke": "volkswagen",
    "navn": "Volkswagen Golf-Serie 1,2",
    "sub": "2012–2012 · TSI 85hk Trendline",
    "score": 0,
    "flipScore": 61,
    "snittPris": 49942,
    "minPris": 49942,
    "maxPris": 49942,
    "snittDager": 22,
    "antallAnnonser": 1,
    "prisEndring": 24332,
    "prisData": [
      59942,
      90614,
      82186,
      87281,
      84274,
      84274
    ],
    "volum": [
      1,
      1,
      1,
      1,
      1,
      1,
      1,
      1,
      1,
      1,
      1,
      1
    ],
    "tags": [
      {
        "t": "God margin",
        "c": "g"
      },
      {
        "t": "Lavt volum",
        "c": "a"
      },
      {
        "t": "Pris opp",
        "c": "a"
      },
      {
        "t": "Under bucket",
        "c": "g"
      },
      {
        "t": "Sterk medianmargin",
        "c": "g"
      },
      {
        "t": "Mange under p25",
        "c": "g"
      }
    ],
    "ai": "Volkswagen Golf-Serie 1,2 — 1 annonser funnet.",
    "avgBucketMedianPrivate": 120000,
    "avgBucketMedianDealer": 99900,
    "avgBucketP25Private": 120000,
    "avgBucketP75Private": 120000,
    "avgLowballTarget": 45697,
    "avgLowballMargin": 74303,
    "avgMedianMargin": 70058,
    "avgCompCount": 6,
    "avgCompSpreadPct": 12,
    "bucketCoverage": 1,
    "bucketDealerCoverage": 1,
    "priceToBucketPct": 42,
    "underBucketShare": 100,
    "p25DealShare": 100,
    "topCompConfidence": "high",
    "confidenceBreakdown": {
      "high": 1
    },
    "primaryValuationSource": "comps_dealer_min",
    "valuationBreakdown": {
      "comps_dealer_min": 1
    },
    "sellerMix": {
      "unknown": 1
    },
    "analysisBaseCount": 1,
    "cohortFilteredCount": 0,
    "bestDealScore": 61,
    "bestMargin": 28175,
    "faktorer": [
      {
        "l": "Etterspørsel",
        "v": 5,
        "c": "#e8a020"
      },
      {
        "l": "Prismargin",
        "v": 100,
        "c": "#3d9960"
      },
      {
        "l": "Likviditet",
        "v": 15,
        "c": "#e8a020"
      },
      {
        "l": "Batteririsiko",
        "v": 20,
        "c": "#e8a020"
      }
    ]
  },
  {
    "id": "volkswagen",
    "merke": "volkswagen",
    "navn": "Volkswagen ID.3 Pure",
    "sub": "2025–2025 · 52kWh 170hk Businessline",
    "score": 70,
    "flipScore": 60,
    "snittPris": 286505,
    "minPris": 286505,
    "maxPris": 286505,
    "snittDager": 14,
    "antallAnnonser": 1,
    "prisEndring": -1748,
    "prisData": [
      272765,
      272069,
      274448,
      267029,
      268287,
      297633,
      271017
    ],
    "volum": [
      1,
      1,
      1,
      1,
      1,
      1,
      1,
      1,
      1,
      1,
      1,
      1
    ],
    "tags": [
      {
        "t": "Lavt volum",
        "c": "a"
      },
      {
        "t": "Mange under p25",
        "c": "g"
      }
    ],
    "ai": "ID.3 Pure Business 2025 med kun 8 500 km til 316 505 kr. God pris for nesten ny bil. Moderat margin mulig.",
    "avgBucketMedianPrivate": 297505,
    "avgBucketMedianDealer": 299900,
    "avgBucketP25Private": 297505,
    "avgBucketP75Private": 297505,
    "avgLowballTarget": 267882,
    "avgLowballMargin": 29623,
    "avgMedianMargin": 11000,
    "avgCompCount": 9,
    "avgCompSpreadPct": 2,
    "bucketCoverage": 1,
    "bucketDealerCoverage": 1,
    "priceToBucketPct": 96,
    "underBucketShare": 100,
    "p25DealShare": 100,
    "topCompConfidence": "high",
    "confidenceBreakdown": {
      "high": 1
    },
    "primaryValuationSource": "bucket_private_min",
    "valuationBreakdown": {
      "bucket_private_min": 1
    },
    "sellerMix": {
      "private_likely": 1
    },
    "analysisBaseCount": 1,
    "cohortFilteredCount": 1,
    "bestDealScore": 60,
    "bestMargin": 455,
    "faktorer": [
      {
        "l": "Etterspørsel",
        "v": 75,
        "c": "#3d9960"
      },
      {
        "l": "Prismargin",
        "v": 1,
        "c": "#e8a020"
      },
      {
        "l": "Likviditet",
        "v": 15,
        "c": "#e8a020"
      },
      {
        "l": "Batteririsiko",
        "v": 92,
        "c": "#3d9960"
      }
    ]
  },
  {
    "id": "teslamodel",
    "merke": "tesla",
    "navn": "Tesla Model Y",
    "sub": "2024–2023 · Long Range AWD - Lav km!",
    "score": 75,
    "flipScore": 59,
    "snittPris": 419708,
    "minPris": 329900,
    "maxPris": 479000,
    "snittDager": 20,
    "antallAnnonser": 21,
    "prisEndring": -15775,
    "prisData": [
      431495,
      413144,
      409471,
      420979,
      425941,
      423295,
      422173,
      415580,
      419436,
      415720
    ],
    "volum": [
      21,
      21,
      21,
      21,
      21,
      21,
      21,
      21,
      21,
      21,
      21,
      21
    ],
    "tags": [
      {
        "t": "Høyt volum",
        "c": "b"
      },
      {
        "t": "Pris ned",
        "c": "g"
      },
      {
        "t": "Under bucket",
        "c": "g"
      },
      {
        "t": "Sterk medianmargin",
        "c": "g"
      },
      {
        "t": "Mange under p25",
        "c": "g"
      }
    ],
    "ai": "Tesla Model Y LR 2024 med 15 200 km til 458 900 kr. Privatsalg. Tilsvarende biler hos forhandler koster 480-510 000 kr. Godt under markedsverdi. Mindre merker nevnt, men ikke alvorlige. Solid gevinstpotensial.",
    "avgBucketMedianPrivate": 471717,
    "avgBucketMedianDealer": 478543,
    "avgBucketP25Private": 458361,
    "avgBucketP75Private": 480819,
    "avgLowballTarget": 394974,
    "avgLowballMargin": 76742,
    "avgMedianMargin": 52009,
    "avgCompCount": 15,
    "avgCompSpreadPct": 8,
    "bucketCoverage": 14,
    "bucketDealerCoverage": 14,
    "priceToBucketPct": 89,
    "underBucketShare": 100,
    "p25DealShare": 93,
    "topCompConfidence": "high",
    "confidenceBreakdown": {
      "high": 14
    },
    "primaryValuationSource": "comps_private_thin_min",
    "valuationBreakdown": {
      "comps_dealer_min": 4,
      "comps_private_min": 4,
      "comps_private_thin_min": 5,
      "bucket_private_min": 1
    },
    "sellerMix": {
      "private_likely": 8,
      "unknown": 13
    },
    "analysisBaseCount": 14,
    "cohortFilteredCount": 14,
    "bestDealScore": 92,
    "bestMargin": 51835,
    "faktorer": [
      {
        "l": "Etterspørsel",
        "v": 80,
        "c": "#3d9960"
      },
      {
        "l": "Prismargin",
        "v": 25,
        "c": "#e8a020"
      },
      {
        "l": "Likviditet",
        "v": 100,
        "c": "#1f5fa6"
      },
      {
        "l": "Batteririsiko",
        "v": 76,
        "c": "#3d9960"
      }
    ]
  },
  {
    "id": "teslamodel",
    "merke": "tesla",
    "navn": "Tesla Model 3",
    "sub": "2020–2021 · AWD",
    "score": 81,
    "flipScore": 59,
    "snittPris": 279634,
    "minPris": 222129,
    "maxPris": 417343,
    "snittDager": 23,
    "antallAnnonser": 16,
    "prisEndring": 1946,
    "prisData": [
      337604,
      306689,
      331508,
      278065,
      336918,
      336798,
      339444,
      338185,
      344473,
      339550
    ],
    "volum": [
      16,
      16,
      16,
      16,
      16,
      16,
      16,
      16,
      16,
      16,
      16,
      16
    ],
    "tags": [
      {
        "t": "Høyt volum",
        "c": "b"
      },
      {
        "t": "Høy score",
        "c": "g"
      },
      {
        "t": "Under bucket",
        "c": "g"
      },
      {
        "t": "Sterk medianmargin",
        "c": "g"
      },
      {
        "t": "Mange under p25",
        "c": "g"
      }
    ],
    "ai": "Tesla Model 3 Performance 2020 til 224k privat. Performance-modell til vanlig LR-pris. Mangler sommerdekk og har noen feil, men STOR verdi for pengene.",
    "avgBucketMedianPrivate": 319559,
    "avgBucketMedianDealer": 327129,
    "avgBucketP25Private": 310684,
    "avgBucketP75Private": 334030,
    "avgLowballTarget": 262604,
    "avgLowballMargin": 56955,
    "avgMedianMargin": 39925,
    "avgCompCount": 7,
    "avgCompSpreadPct": 11,
    "bucketCoverage": 7,
    "bucketDealerCoverage": 7,
    "priceToBucketPct": 88,
    "underBucketShare": 100,
    "p25DealShare": 100,
    "topCompConfidence": "high",
    "confidenceBreakdown": {
      "high": 6,
      "medium": 1
    },
    "primaryValuationSource": "comps_dealer_min",
    "valuationBreakdown": {
      "comps_dealer_min": 3,
      "comps_private_thin_min": 2,
      "comps_private_min": 1,
      "bucket_private_min": 1
    },
    "sellerMix": {
      "private_likely": 6,
      "unknown": 10
    },
    "analysisBaseCount": 7,
    "cohortFilteredCount": 7,
    "bestDealScore": 85,
    "bestMargin": 30865,
    "faktorer": [
      {
        "l": "Etterspørsel",
        "v": 86,
        "c": "#3d9960"
      },
      {
        "l": "Prismargin",
        "v": 38,
        "c": "#e8a020"
      },
      {
        "l": "Likviditet",
        "v": 100,
        "c": "#1f5fa6"
      },
      {
        "l": "Batteririsiko",
        "v": 60,
        "c": "#3d9960"
      }
    ]
  },
  {
    "id": "volkswagen",
    "merke": "volkswagen",
    "navn": "Volkswagen ID.3 1st",
    "sub": "2021–2020 · Plus Pro 204hk, 1 eier",
    "score": 88,
    "flipScore": 59,
    "snittPris": 181355,
    "minPris": 170000,
    "maxPris": 189532,
    "snittDager": 14,
    "antallAnnonser": 3,
    "prisEndring": -2331,
    "prisData": [
      208571,
      208769,
      208096,
      208656,
      206183,
      216199,
      206240
    ],
    "volum": [
      3,
      3,
      3,
      3,
      3,
      3,
      3,
      3,
      3,
      3,
      3,
      3
    ],
    "tags": [
      {
        "t": "Høy score",
        "c": "g"
      },
      {
        "t": "Under bucket",
        "c": "g"
      },
      {
        "t": "Sterk medianmargin",
        "c": "g"
      },
      {
        "t": "Mange under p25",
        "c": "g"
      }
    ],
    "ai": "VW ID.3 1st Plus Pro til 189 532 kr privat. Kun 56 639 km, 1 eier, garasjebilt. Veldig god pris. Tilsvarende selges for 230-250 000 kr hos forhandler. Svært god margin, populær elbil.",
    "avgBucketMedianPrivate": 222416,
    "avgBucketMedianDealer": 209300,
    "avgBucketP25Private": 210974,
    "avgBucketP75Private": 233858,
    "avgLowballTarget": 170473,
    "avgLowballMargin": 51943,
    "avgMedianMargin": 41061,
    "avgCompCount": 11,
    "avgCompSpreadPct": 10,
    "bucketCoverage": 3,
    "bucketDealerCoverage": 3,
    "priceToBucketPct": 82,
    "underBucketShare": 100,
    "p25DealShare": 100,
    "topCompConfidence": "high",
    "confidenceBreakdown": {
      "high": 3
    },
    "primaryValuationSource": "comps_dealer_min",
    "valuationBreakdown": {
      "bucket_dealer_min": 1,
      "comps_dealer_min": 2
    },
    "sellerMix": {
      "private_likely": 2,
      "unknown": 1
    },
    "analysisBaseCount": 3,
    "cohortFilteredCount": 1,
    "bestDealScore": 76,
    "bestMargin": 11923,
    "faktorer": [
      {
        "l": "Etterspørsel",
        "v": 93,
        "c": "#3d9960"
      },
      {
        "l": "Prismargin",
        "v": 24,
        "c": "#e8a020"
      },
      {
        "l": "Likviditet",
        "v": 45,
        "c": "#e8a020"
      },
      {
        "l": "Batteririsiko",
        "v": 52,
        "c": "#e8a020"
      }
    ]
  },
  {
    "id": "toyotayari",
    "merke": "toyota",
    "navn": "Toyota Yaris 1,0",
    "sub": "2013–2013 · Active",
    "score": 0,
    "flipScore": 59,
    "snittPris": 61942,
    "minPris": 61942,
    "maxPris": 61942,
    "snittDager": 22,
    "antallAnnonser": 1,
    "prisEndring": -14874,
    "prisData": [
      66295,
      66295,
      65971,
      82500,
      51421,
      51421
    ],
    "volum": [
      1,
      1,
      1,
      1,
      1,
      1,
      1,
      1,
      1,
      1,
      1,
      1
    ],
    "tags": [
      {
        "t": "God margin",
        "c": "g"
      },
      {
        "t": "Lavt volum",
        "c": "a"
      },
      {
        "t": "Pris ned",
        "c": "g"
      },
      {
        "t": "Under bucket",
        "c": "g"
      },
      {
        "t": "Sterk medianmargin",
        "c": "g"
      },
      {
        "t": "Mange under p25",
        "c": "g"
      }
    ],
    "ai": "Toyota Yaris 1,0 — 1 annonser funnet.",
    "avgBucketMedianPrivate": 117945,
    "avgBucketMedianDealer": 115000,
    "avgBucketP25Private": 117418,
    "avgBucketP75Private": 118473,
    "avgLowballTarget": 56987,
    "avgLowballMargin": 60958,
    "avgMedianMargin": 56003,
    "avgCompCount": 5,
    "avgCompSpreadPct": 24,
    "bucketCoverage": 1,
    "bucketDealerCoverage": 1,
    "priceToBucketPct": 53,
    "underBucketShare": 100,
    "p25DealShare": 100,
    "topCompConfidence": "medium",
    "confidenceBreakdown": {
      "medium": 1
    },
    "primaryValuationSource": "bucket_dealer_min",
    "valuationBreakdown": {
      "bucket_dealer_min": 1
    },
    "sellerMix": {
      "unknown": 1
    },
    "analysisBaseCount": 1,
    "cohortFilteredCount": 0,
    "bestDealScore": 59,
    "bestMargin": 38013,
    "faktorer": [
      {
        "l": "Etterspørsel",
        "v": 5,
        "c": "#e8a020"
      },
      {
        "l": "Prismargin",
        "v": 100,
        "c": "#3d9960"
      },
      {
        "l": "Likviditet",
        "v": 15,
        "c": "#e8a020"
      },
      {
        "l": "Batteririsiko",
        "v": 20,
        "c": "#e8a020"
      }
    ]
  },
  {
    "id": "volkswagen",
    "merke": "volkswagen",
    "navn": "Volkswagen Golf-Serie E-Golf",
    "sub": "2018–2016 · Diverse",
    "score": 41,
    "flipScore": 57,
    "snittPris": 99732,
    "minPris": 89532,
    "maxPris": 109932,
    "snittDager": 16,
    "antallAnnonser": 2,
    "prisEndring": 3905,
    "prisData": [
      135774,
      135010,
      136029,
      133359,
      133529,
      143083,
      139679
    ],
    "volum": [
      2,
      2,
      2,
      2,
      2,
      2,
      2,
      2,
      2,
      2,
      2,
      2
    ],
    "tags": [
      {
        "t": "Lavt volum",
        "c": "a"
      },
      {
        "t": "Under bucket",
        "c": "g"
      },
      {
        "t": "Mange under p25",
        "c": "g"
      }
    ],
    "ai": "VW e-Golf 2018 med 76 000 km til 114 532 kr. Veldig god pris! Tilsvarende e-Golfer selges for 140-160 000 kr. AC/ladekontakt reparert - bra. God flip-mulighet.",
    "avgBucketMedianPrivate": 109932,
    "avgBucketMedianDealer": 131748,
    "avgBucketP25Private": 109932,
    "avgBucketP75Private": 109932,
    "avgLowballTarget": 93748,
    "avgLowballMargin": 30718,
    "avgMedianMargin": 24734,
    "avgCompCount": 7,
    "avgCompSpreadPct": 19,
    "bucketCoverage": 1,
    "bucketDealerCoverage": 2,
    "priceToBucketPct": 91,
    "underBucketShare": 100,
    "p25DealShare": 50,
    "topCompConfidence": "high",
    "confidenceBreakdown": {
      "high": 1,
      "medium": 1
    },
    "primaryValuationSource": "comps_dealer_min",
    "valuationBreakdown": {
      "comps_dealer_min": 1,
      "bucket_private_min": 1
    },
    "sellerMix": {
      "private_likely": 1,
      "unknown": 1
    },
    "analysisBaseCount": 2,
    "cohortFilteredCount": 2,
    "bestDealScore": 76,
    "bestMargin": 15439,
    "faktorer": [
      {
        "l": "Etterspørsel",
        "v": 46,
        "c": "#e8a020"
      },
      {
        "l": "Prismargin",
        "v": 52,
        "c": "#e8a020"
      },
      {
        "l": "Likviditet",
        "v": 30,
        "c": "#e8a020"
      },
      {
        "l": "Batteririsiko",
        "v": 28,
        "c": "#e8a020"
      }
    ]
  },
  {
    "id": "volkswagen",
    "merke": "volkswagen",
    "navn": "Volkswagen ID.4 Pro",
    "sub": "2023–2022 · Limited 77kWh 204hk",
    "score": 79,
    "flipScore": 57,
    "snittPris": 289032,
    "minPris": 273532,
    "maxPris": 304532,
    "snittDager": 5,
    "antallAnnonser": 2,
    "prisEndring": -3783,
    "prisData": [
      395047,
      396563,
      390213,
      388302,
      391398,
      331925,
      391264
    ],
    "volum": [
      2,
      2,
      2,
      2,
      2,
      2,
      2,
      2,
      2,
      2,
      2,
      2
    ],
    "tags": [
      {
        "t": "Lavt volum",
        "c": "a"
      },
      {
        "t": "Under bucket",
        "c": "g"
      },
      {
        "t": "Sterk medianmargin",
        "c": "g"
      },
      {
        "t": "Mange under p25",
        "c": "g"
      }
    ],
    "ai": "Svært lav pris (304 532 kr) for en 2023 ID.4 Pro Limited med 38 000 km. Markedsverdi er 360 000–370 000 kr hos forhandler. Ingen skader oppgitt. Høy margin og god etterspørsel etter ID.4.",
    "avgBucketMedianPrivate": 421762,
    "avgBucketMedianDealer": 324450,
    "avgBucketP25Private": 401390,
    "avgBucketP75Private": 442134,
    "avgLowballTarget": 274580,
    "avgLowballMargin": 147182,
    "avgMedianMargin": 132730,
    "avgCompCount": 20,
    "avgCompSpreadPct": 15,
    "bucketCoverage": 2,
    "bucketDealerCoverage": 2,
    "priceToBucketPct": 69,
    "underBucketShare": 100,
    "p25DealShare": 100,
    "topCompConfidence": "high",
    "confidenceBreakdown": {
      "high": 2
    },
    "primaryValuationSource": "bucket_dealer_min",
    "valuationBreakdown": {
      "bucket_dealer_min": 1,
      "comps_dealer_min": 1
    },
    "sellerMix": {
      "private_likely": 1,
      "unknown": 1
    },
    "analysisBaseCount": 2,
    "cohortFilteredCount": 2,
    "bestDealScore": 66,
    "bestMargin": 12483,
    "faktorer": [
      {
        "l": "Etterspørsel",
        "v": 84,
        "c": "#3d9960"
      },
      {
        "l": "Prismargin",
        "v": 23,
        "c": "#e8a020"
      },
      {
        "l": "Likviditet",
        "v": 30,
        "c": "#e8a020"
      },
      {
        "l": "Batteririsiko",
        "v": 76,
        "c": "#3d9960"
      }
    ]
  },
  {
    "id": "toyotarav4",
    "merke": "toyota",
    "navn": "Toyota RAV4 Hybrid",
    "sub": "2020–2021 · 2WD Style aut",
    "score": 43,
    "flipScore": 57,
    "snittPris": 342233,
    "minPris": 309532,
    "maxPris": 374934,
    "snittDager": 18,
    "antallAnnonser": 2,
    "prisEndring": -12004,
    "prisData": [
      481655,
      484287,
      480938,
      475604,
      469507,
      469651
    ],
    "volum": [
      2,
      2,
      2,
      2,
      2,
      2,
      2,
      2,
      2,
      2,
      2,
      2
    ],
    "tags": [
      {
        "t": "Lavt volum",
        "c": "a"
      },
      {
        "t": "Pris ned",
        "c": "g"
      },
      {
        "t": "Under bucket",
        "c": "g"
      },
      {
        "t": "Sterk medianmargin",
        "c": "g"
      },
      {
        "t": "Mange under p25",
        "c": "g"
      }
    ],
    "ai": "RAV4 Hybrid 2020 privat selger, kun 66k km, fullt utstyr. Pris 319 532 kr er UNDER markedsverdi for privat – forhandlere tar 360k+. Ingen skader. Stor margin mulig.",
    "avgBucketMedianPrivate": 446766,
    "avgBucketMedianDealer": 373500,
    "avgBucketP25Private": 424899,
    "avgBucketP75Private": 473725,
    "avgLowballTarget": 319825,
    "avgLowballMargin": 126942,
    "avgMedianMargin": 104533,
    "avgCompCount": 11,
    "avgCompSpreadPct": 7,
    "bucketCoverage": 2,
    "bucketDealerCoverage": 2,
    "priceToBucketPct": 77,
    "underBucketShare": 100,
    "p25DealShare": 100,
    "topCompConfidence": "high",
    "confidenceBreakdown": {
      "high": 2
    },
    "primaryValuationSource": "bucket_dealer_min",
    "valuationBreakdown": {
      "bucket_dealer_min": 1,
      "comps_dealer_min": 1
    },
    "sellerMix": {
      "unknown": 1,
      "private_likely": 1
    },
    "analysisBaseCount": 2,
    "cohortFilteredCount": 1,
    "bestDealScore": 62,
    "bestMargin": 17923,
    "faktorer": [
      {
        "l": "Etterspørsel",
        "v": 48,
        "c": "#e8a020"
      },
      {
        "l": "Prismargin",
        "v": 24,
        "c": "#e8a020"
      },
      {
        "l": "Likviditet",
        "v": 30,
        "c": "#e8a020"
      },
      {
        "l": "Batteririsiko",
        "v": 60,
        "c": "#3d9960"
      }
    ]
  },
  {
    "id": "volkswagen",
    "merke": "volkswagen",
    "navn": "Volkswagen ID.3 Pro",
    "sub": "2021–2021 · Performance Life",
    "score": 78,
    "flipScore": 57,
    "snittPris": 186983,
    "minPris": 179532,
    "maxPris": 194434,
    "snittDager": 11,
    "antallAnnonser": 2,
    "prisEndring": -681,
    "prisData": [
      272256,
      271318,
      270209,
      271567,
      271356,
      280343,
      271575
    ],
    "volum": [
      2,
      2,
      2,
      2,
      2,
      2,
      2,
      2,
      2,
      2,
      2,
      2
    ],
    "tags": [
      {
        "t": "Lavt volum",
        "c": "a"
      },
      {
        "t": "Under bucket",
        "c": "g"
      },
      {
        "t": "Sterk medianmargin",
        "c": "g"
      },
      {
        "t": "Mange under p25",
        "c": "g"
      }
    ],
    "ai": "2021 ID.3 med 62 000 km til 179 532 kr. Markedspris for tilsvarende biler er 195 000-210 000 kr. God margin, men sjekk om det er noen skader eller feil.",
    "avgBucketMedianPrivate": 223883,
    "avgBucketMedianDealer": 202925,
    "avgBucketP25Private": 205458,
    "avgBucketP75Private": 242308,
    "avgLowballTarget": 175278,
    "avgLowballMargin": 48605,
    "avgMedianMargin": 36900,
    "avgCompCount": 9,
    "avgCompSpreadPct": 13,
    "bucketCoverage": 2,
    "bucketDealerCoverage": 2,
    "priceToBucketPct": 84,
    "underBucketShare": 100,
    "p25DealShare": 100,
    "topCompConfidence": "high",
    "confidenceBreakdown": {
      "high": 2
    },
    "primaryValuationSource": "bucket_dealer_min",
    "valuationBreakdown": {
      "bucket_dealer_min": 2
    },
    "sellerMix": {
      "private_likely": 1,
      "unknown": 1
    },
    "analysisBaseCount": 2,
    "cohortFilteredCount": 1,
    "bestDealScore": 59,
    "bestMargin": 6773,
    "faktorer": [
      {
        "l": "Etterspørsel",
        "v": 83,
        "c": "#3d9960"
      },
      {
        "l": "Prismargin",
        "v": 18,
        "c": "#e8a020"
      },
      {
        "l": "Likviditet",
        "v": 30,
        "c": "#e8a020"
      },
      {
        "l": "Batteririsiko",
        "v": 60,
        "c": "#3d9960"
      }
    ]
  },
  {
    "id": "nissanleaf",
    "merke": "nissan",
    "navn": "Nissan Leaf 2023",
    "sub": "2023–2023 · ∙ 36 500 km ∙ El ∙ 285 km rekkevidde",
    "score": 85,
    "flipScore": 57,
    "snittPris": 165000,
    "minPris": 165000,
    "maxPris": 165000,
    "snittDager": 5,
    "antallAnnonser": 1,
    "prisEndring": -1252,
    "prisData": [
      167505,
      167505,
      167505,
      167505,
      165000,
      167505,
      166253
    ],
    "volum": [
      1,
      1,
      1,
      1,
      1,
      1,
      1,
      1,
      1,
      1,
      1,
      1
    ],
    "tags": [
      {
        "t": "Lavt volum",
        "c": "a"
      },
      {
        "t": "Høy score",
        "c": "g"
      },
      {
        "t": "Under bucket",
        "c": "g"
      },
      {
        "t": "Sterk medianmargin",
        "c": "g"
      },
      {
        "t": "Mange under p25",
        "c": "g"
      }
    ],
    "ai": "Meget lav km for en 2023-modell og prisen er svært konkurransedyktig. Tilsvarende biler hos forhandler koster ofte 180-190 000 kr. Dette er et godt kjøp med solid videresalgspotensial, spesielt med tanke på lav km og nytt årsmodell.",
    "avgBucketMedianPrivate": 212343,
    "avgBucketMedianDealer": 209900,
    "avgBucketP25Private": 193672,
    "avgBucketP75Private": 229424,
    "avgLowballTarget": 156750,
    "avgLowballMargin": 55593,
    "avgMedianMargin": 47343,
    "avgCompCount": 25,
    "avgCompSpreadPct": 16,
    "bucketCoverage": 1,
    "bucketDealerCoverage": 1,
    "priceToBucketPct": 78,
    "underBucketShare": 100,
    "p25DealShare": 100,
    "topCompConfidence": "high",
    "confidenceBreakdown": {
      "high": 1
    },
    "primaryValuationSource": "comps_private_min",
    "valuationBreakdown": {
      "comps_private_min": 1
    },
    "sellerMix": {
      "private_likely": 1
    },
    "analysisBaseCount": 1,
    "cohortFilteredCount": 1,
    "bestDealScore": 57,
    "bestMargin": 5353,
    "faktorer": [
      {
        "l": "Etterspørsel",
        "v": 90,
        "c": "#3d9960"
      },
      {
        "l": "Prismargin",
        "v": 16,
        "c": "#e8a020"
      },
      {
        "l": "Likviditet",
        "v": 15,
        "c": "#e8a020"
      },
      {
        "l": "Batteririsiko",
        "v": 76,
        "c": "#3d9960"
      }
    ]
  },
  {
    "id": "volkswagen",
    "merke": "volkswagen",
    "navn": "Volkswagen Golf Sportsvan",
    "sub": "2015–2015 · 1,2TSI 110hk Highline DSG 76.000km 1eier Massasje Ny Eu",
    "score": 0,
    "flipScore": 57,
    "snittPris": 119942,
    "minPris": 119942,
    "maxPris": 119942,
    "snittDager": 22,
    "antallAnnonser": 1,
    "prisEndring": -1500,
    "prisData": [
      160431,
      160028,
      154028,
      151942,
      158931,
      158931
    ],
    "volum": [
      1,
      1,
      1,
      1,
      1,
      1,
      1,
      1,
      1,
      1,
      1,
      1
    ],
    "tags": [
      {
        "t": "Lavt volum",
        "c": "a"
      },
      {
        "t": "Under bucket",
        "c": "g"
      },
      {
        "t": "Sterk medianmargin",
        "c": "g"
      },
      {
        "t": "Mange under p25",
        "c": "g"
      }
    ],
    "ai": "Volkswagen Golf Sportsvan — 1 annonser funnet.",
    "avgBucketMedianPrivate": 159942,
    "avgBucketMedianDealer": 159000,
    "avgBucketP25Private": 159942,
    "avgBucketP75Private": 159942,
    "avgLowballTarget": 112745,
    "avgLowballMargin": 47197,
    "avgMedianMargin": 40000,
    "avgCompCount": 4,
    "avgCompSpreadPct": 44,
    "bucketCoverage": 1,
    "bucketDealerCoverage": 1,
    "priceToBucketPct": 75,
    "underBucketShare": 100,
    "p25DealShare": 100,
    "topCompConfidence": "low",
    "confidenceBreakdown": {
      "low": 1
    },
    "primaryValuationSource": "comps_dealer_min",
    "valuationBreakdown": {
      "comps_dealer_min": 1
    },
    "sellerMix": {
      "private_likely": 1
    },
    "analysisBaseCount": 1,
    "cohortFilteredCount": 1,
    "bestDealScore": 57,
    "bestMargin": 12728,
    "faktorer": [
      {
        "l": "Etterspørsel",
        "v": 5,
        "c": "#e8a020"
      },
      {
        "l": "Prismargin",
        "v": 53,
        "c": "#e8a020"
      },
      {
        "l": "Likviditet",
        "v": 15,
        "c": "#e8a020"
      },
      {
        "l": "Batteririsiko",
        "v": 20,
        "c": "#e8a020"
      }
    ]
  },
  {
    "id": "hyundaikon",
    "merke": "hyundai",
    "navn": "Hyundai Kona Trend",
    "sub": "2022–2022 · SR, nettopp EU-godkjent, lav km-stand",
    "score": 60,
    "flipScore": 56,
    "snittPris": 185000,
    "minPris": 185000,
    "maxPris": 185000,
    "snittDager": 1,
    "antallAnnonser": 1,
    "prisEndring": -6786,
    "prisData": [
      225662,
      226103,
      221513,
      219782,
      220251,
      217933,
      218876
    ],
    "volum": [
      1,
      1,
      1,
      1,
      1,
      1,
      1,
      1,
      1,
      1,
      1,
      1
    ],
    "tags": [
      {
        "t": "God margin",
        "c": "g"
      },
      {
        "t": "Lavt volum",
        "c": "a"
      },
      {
        "t": "Pris ned",
        "c": "g"
      },
      {
        "t": "Under bucket",
        "c": "g"
      },
      {
        "t": "Sterk medianmargin",
        "c": "g"
      },
      {
        "t": "Mange under p25",
        "c": "g"
      }
    ],
    "ai": "Pris på 185 000 kr er godt under markedsverdi på 221 343 kr, og gir estimert gevinst på 25 798 kr (14%) etter kostnader. Selger er ukjent, noe som øker risikoen. Ingen skader oppgitt.",
    "avgBucketMedianPrivate": 224532,
    "avgBucketMedianDealer": 228900,
    "avgBucketP25Private": 224532,
    "avgBucketP75Private": 224532,
    "avgLowballTarget": 175750,
    "avgLowballMargin": 48782,
    "avgMedianMargin": 39532,
    "avgCompCount": 9,
    "avgCompSpreadPct": 6,
    "bucketCoverage": 1,
    "bucketDealerCoverage": 1,
    "priceToBucketPct": 82,
    "underBucketShare": 100,
    "p25DealShare": 100,
    "topCompConfidence": "high",
    "confidenceBreakdown": {
      "high": 1
    },
    "primaryValuationSource": "comps_dealer_min",
    "valuationBreakdown": {
      "comps_dealer_min": 1
    },
    "sellerMix": {
      "unknown": 1
    },
    "analysisBaseCount": 1,
    "cohortFilteredCount": 1,
    "bestDealScore": 56,
    "bestMargin": 25661,
    "faktorer": [
      {
        "l": "Etterspørsel",
        "v": 65,
        "c": "#e8a020"
      },
      {
        "l": "Prismargin",
        "v": 69,
        "c": "#3d9960"
      },
      {
        "l": "Likviditet",
        "v": 15,
        "c": "#e8a020"
      },
      {
        "l": "Batteririsiko",
        "v": 68,
        "c": "#3d9960"
      }
    ]
  },
  {
    "id": "hyundaikon",
    "merke": "hyundai",
    "navn": "Hyundai Kona Premium",
    "sub": "2019–2020 · Diverse",
    "score": 78,
    "flipScore": 55,
    "snittPris": 249266,
    "minPris": 249000,
    "maxPris": 249532,
    "snittDager": 12,
    "antallAnnonser": 5,
    "prisEndring": 10055,
    "prisData": [
      295532,
      291875,
      292328,
      291396,
      307402,
      262768,
      305587
    ],
    "volum": [
      5,
      5,
      5,
      5,
      5,
      5,
      5,
      5,
      5,
      5,
      5,
      5
    ],
    "tags": [
      {
        "t": "Høyt volum",
        "c": "b"
      },
      {
        "t": "Pris opp",
        "c": "a"
      },
      {
        "t": "Under bucket",
        "c": "g"
      },
      {
        "t": "Sterk medianmargin",
        "c": "g"
      },
      {
        "t": "Mange under p25",
        "c": "g"
      }
    ],
    "ai": "Hyundai Kona Premium — 5 annonser funnet.",
    "avgBucketMedianPrivate": 298627,
    "avgBucketMedianDealer": 279225,
    "avgBucketP25Private": 286313,
    "avgBucketP75Private": 310940,
    "avgLowballTarget": 236803,
    "avgLowballMargin": 61824,
    "avgMedianMargin": 49361,
    "avgCompCount": 6,
    "avgCompSpreadPct": 13,
    "bucketCoverage": 2,
    "bucketDealerCoverage": 2,
    "priceToBucketPct": 83,
    "underBucketShare": 100,
    "p25DealShare": 100,
    "topCompConfidence": "high",
    "confidenceBreakdown": {
      "high": 1,
      "medium": 1
    },
    "primaryValuationSource": "comps_dealer_min",
    "valuationBreakdown": {
      "comps_dealer_min": 2
    },
    "sellerMix": {
      "private_likely": 4,
      "unknown": 1
    },
    "analysisBaseCount": 2,
    "cohortFilteredCount": 2,
    "bestDealScore": 73,
    "bestMargin": 22737,
    "faktorer": [
      {
        "l": "Etterspørsel",
        "v": 83,
        "c": "#3d9960"
      },
      {
        "l": "Prismargin",
        "v": 9,
        "c": "#e8a020"
      },
      {
        "l": "Likviditet",
        "v": 75,
        "c": "#1f5fa6"
      },
      {
        "l": "Batteririsiko",
        "v": 52,
        "c": "#e8a020"
      }
    ]
  },
  {
    "id": "nissanleaf",
    "merke": "nissan",
    "navn": "Nissan Leaf 2020",
    "sub": "2020–2020 · ∙ 41 000 km ∙ El ∙ 270 km rekkevidde",
    "score": 88,
    "flipScore": 54,
    "snittPris": 138532,
    "minPris": 138532,
    "maxPris": 138532,
    "snittDager": 32,
    "antallAnnonser": 1,
    "prisEndring": 20000,
    "prisData": [
      138532,
      138532,
      138532,
      138532,
      138532,
      158532,
      158532
    ],
    "volum": [
      1,
      1,
      1,
      1,
      1,
      1,
      1,
      1,
      1,
      1,
      1,
      1
    ],
    "tags": [
      {
        "t": "Lavt volum",
        "c": "a"
      },
      {
        "t": "Høy score",
        "c": "g"
      },
      {
        "t": "Pris opp",
        "c": "a"
      },
      {
        "t": "Under bucket",
        "c": "g"
      },
      {
        "t": "Sterk medianmargin",
        "c": "g"
      },
      {
        "t": "Mange under p25",
        "c": "g"
      }
    ],
    "ai": "UTMERKET kjøp! Leaf 2020 med kun 41k km til 138.532 kr. Dette er langt under markedsverdi. Svært god margin mulig. Privatsalg uten kjente feil.",
    "avgBucketMedianPrivate": 169532,
    "avgBucketMedianDealer": 169000,
    "avgBucketP25Private": 158532,
    "avgBucketP75Private": 174532,
    "avgLowballTarget": 130220,
    "avgLowballMargin": 39312,
    "avgMedianMargin": 31000,
    "avgCompCount": 25,
    "avgCompSpreadPct": 20,
    "bucketCoverage": 1,
    "bucketDealerCoverage": 1,
    "priceToBucketPct": 82,
    "underBucketShare": 100,
    "p25DealShare": 100,
    "topCompConfidence": "high",
    "confidenceBreakdown": {
      "high": 1
    },
    "primaryValuationSource": "comps_private_min",
    "valuationBreakdown": {
      "comps_private_min": 1
    },
    "sellerMix": {
      "unknown": 1
    },
    "analysisBaseCount": 1,
    "cohortFilteredCount": 1,
    "bestDealScore": 54,
    "bestMargin": 10015,
    "faktorer": [
      {
        "l": "Etterspørsel",
        "v": 93,
        "c": "#3d9960"
      },
      {
        "l": "Prismargin",
        "v": 36,
        "c": "#e8a020"
      },
      {
        "l": "Likviditet",
        "v": 15,
        "c": "#e8a020"
      },
      {
        "l": "Batteririsiko",
        "v": 52,
        "c": "#e8a020"
      }
    ]
  },
  {
    "id": "volkswagen",
    "merke": "volkswagen",
    "navn": "Volkswagen Golf-Serie Exclusive",
    "sub": "2020–2020 · (K)",
    "score": 85,
    "flipScore": 54,
    "snittPris": 129999,
    "minPris": 129999,
    "maxPris": 129999,
    "snittDager": 20,
    "antallAnnonser": 1,
    "prisEndring": 1518,
    "prisData": [
      151108,
      150752,
      148433,
      146636,
      143463,
      159000,
      152626
    ],
    "volum": [
      1,
      1,
      1,
      1,
      1,
      1,
      1,
      1,
      1,
      1,
      1,
      1
    ],
    "tags": [
      {
        "t": "Lavt volum",
        "c": "a"
      },
      {
        "t": "Høy score",
        "c": "g"
      },
      {
        "t": "Under bucket",
        "c": "g"
      },
      {
        "t": "Mange under p25",
        "c": "g"
      }
    ],
    "ai": "e-Golf Exclusive med lang batterigaranti og norsk forhandlerhistorie. Ingen feil, lav km. Prisen er SVÆRT god - under markedsverdi for tilsvarende biler hos forhandlere.",
    "avgBucketMedianPrivate": 154532,
    "avgBucketMedianDealer": 149400,
    "avgBucketP25Private": 154532,
    "avgBucketP75Private": 154532,
    "avgLowballTarget": 122199,
    "avgLowballMargin": 32333,
    "avgMedianMargin": 24533,
    "avgCompCount": 3,
    "avgCompSpreadPct": 6,
    "bucketCoverage": 1,
    "bucketDealerCoverage": 1,
    "priceToBucketPct": 84,
    "underBucketShare": 100,
    "p25DealShare": 100,
    "topCompConfidence": "low",
    "confidenceBreakdown": {
      "low": 1
    },
    "primaryValuationSource": "comps_dealer_min",
    "valuationBreakdown": {
      "comps_dealer_min": 1
    },
    "sellerMix": {
      "private_likely": 1
    },
    "analysisBaseCount": 1,
    "cohortFilteredCount": 1,
    "bestDealScore": 54,
    "bestMargin": 10267,
    "faktorer": [
      {
        "l": "Etterspørsel",
        "v": 90,
        "c": "#3d9960"
      },
      {
        "l": "Prismargin",
        "v": 39,
        "c": "#e8a020"
      },
      {
        "l": "Likviditet",
        "v": 15,
        "c": "#e8a020"
      },
      {
        "l": "Batteririsiko",
        "v": 52,
        "c": "#e8a020"
      }
    ]
  },
  {
    "id": "volkswagen",
    "merke": "volkswagen",
    "navn": "Volkswagen Golf-Serie Golf",
    "sub": "2019–2019 · 1,0 BlueMotion Technology GOLF",
    "score": 80,
    "flipScore": 54,
    "snittPris": 199900,
    "minPris": 199900,
    "maxPris": 199900,
    "snittDager": 14,
    "antallAnnonser": 1,
    "prisEndring": 36225,
    "prisData": [
      156058,
      156058,
      196411,
      194783,
      194783,
      69800,
      192283
    ],
    "volum": [
      1,
      1,
      1,
      1,
      1,
      1,
      1,
      1,
      1,
      1,
      1,
      1
    ],
    "tags": [
      {
        "t": "God margin",
        "c": "g"
      },
      {
        "t": "Lavt volum",
        "c": "a"
      },
      {
        "t": "Høy score",
        "c": "g"
      },
      {
        "t": "Pris opp",
        "c": "a"
      }
    ],
    "ai": "Priset til 199 900 kr for en 2019-modell Golf Highline med 74 250 km. Dette er en privatperson, og tilsvarende biler hos forhandler koster 220-250 000 kr. Godt utstyrt (ACC, ryggekamera, navigasjon), nylig service og nye bremser. God margin.",
    "avgBucketMedianPrivate": null,
    "avgBucketMedianDealer": null,
    "avgBucketP25Private": null,
    "avgBucketP75Private": null,
    "avgLowballTarget": 189905,
    "avgLowballMargin": -189905,
    "avgMedianMargin": null,
    "avgCompCount": 0,
    "avgCompSpreadPct": null,
    "bucketCoverage": 0,
    "bucketDealerCoverage": 0,
    "priceToBucketPct": null,
    "underBucketShare": 0,
    "p25DealShare": 0,
    "topCompConfidence": "low",
    "confidenceBreakdown": {
      "low": 1
    },
    "primaryValuationSource": "ai_fallback",
    "valuationBreakdown": {
      "ai_fallback": 1
    },
    "sellerMix": {
      "private_likely": 1
    },
    "analysisBaseCount": 1,
    "cohortFilteredCount": 0,
    "bestDealScore": 54,
    "bestMargin": 27555,
    "faktorer": [
      {
        "l": "Etterspørsel",
        "v": 85,
        "c": "#3d9960"
      },
      {
        "l": "Prismargin",
        "v": 69,
        "c": "#3d9960"
      },
      {
        "l": "Likviditet",
        "v": 15,
        "c": "#e8a020"
      },
      {
        "l": "Batteririsiko",
        "v": 44,
        "c": "#e8a020"
      }
    ]
  },
  {
    "id": "volkswagen",
    "merke": "volkswagen",
    "navn": "Volkswagen Golf-Serie 1,4",
    "sub": "2021–2021 · TSI 245hk",
    "score": 75,
    "flipScore": 53,
    "snittPris": 284532,
    "minPris": 284532,
    "maxPris": 284532,
    "snittDager": 15,
    "antallAnnonser": 1,
    "prisEndring": 9897,
    "prisData": [
      217446,
      204553,
      204917,
      222245,
      223921,
      227343
    ],
    "volum": [
      1,
      1,
      1,
      1,
      1,
      1,
      1,
      1,
      1,
      1,
      1,
      1
    ],
    "tags": [
      {
        "t": "Lavt volum",
        "c": "a"
      },
      {
        "t": "Pris opp",
        "c": "a"
      },
      {
        "t": "Sterk medianmargin",
        "c": "g"
      }
    ],
    "ai": "2021 Golf GTI (1.4 TSI 245 hk) med 44 000 km, priset til 284 532 kr. Sjelden og sportslig modell med ettermonterte H&K senkefjærer og gode felger. Ingen kjente feil/skader. Godt potensial for videresalg til entusiaster, med god margin.",
    "avgBucketMedianPrivate": null,
    "avgBucketMedianDealer": 324000,
    "avgBucketP25Private": null,
    "avgBucketP75Private": null,
    "avgLowballTarget": 270305,
    "avgLowballMargin": 53695,
    "avgMedianMargin": 39468,
    "avgCompCount": 4,
    "avgCompSpreadPct": 31,
    "bucketCoverage": 0,
    "bucketDealerCoverage": 1,
    "priceToBucketPct": null,
    "underBucketShare": 100,
    "p25DealShare": 0,
    "topCompConfidence": "low",
    "confidenceBreakdown": {
      "low": 1
    },
    "primaryValuationSource": "comps_dealer_min",
    "valuationBreakdown": {
      "comps_dealer_min": 1
    },
    "sellerMix": {
      "private_likely": 1
    },
    "analysisBaseCount": 1,
    "cohortFilteredCount": 1,
    "bestDealScore": 53,
    "bestMargin": 13663,
    "faktorer": [
      {
        "l": "Etterspørsel",
        "v": 80,
        "c": "#3d9960"
      },
      {
        "l": "Prismargin",
        "v": 24,
        "c": "#e8a020"
      },
      {
        "l": "Likviditet",
        "v": 15,
        "c": "#e8a020"
      },
      {
        "l": "Batteririsiko",
        "v": 60,
        "c": "#3d9960"
      }
    ]
  },
  {
    "id": "toyotayari",
    "merke": "toyota",
    "navn": "Toyota Yaris Cross",
    "sub": "2022–2022 · 1,5 Hybrid AWD-i Active Tech",
    "score": 82,
    "flipScore": 52,
    "snittPris": 305000,
    "minPris": 305000,
    "maxPris": 305000,
    "snittDager": 2,
    "antallAnnonser": 1,
    "prisEndring": -8572,
    "prisData": [
      375608,
      374227,
      372041,
      371559,
      367208,
      351071,
      367036
    ],
    "volum": [
      1,
      1,
      1,
      1,
      1,
      1,
      1,
      1,
      1,
      1,
      1,
      1
    ],
    "tags": [
      {
        "t": "God margin",
        "c": "g"
      },
      {
        "t": "Lavt volum",
        "c": "a"
      },
      {
        "t": "Høy score",
        "c": "g"
      },
      {
        "t": "Pris ned",
        "c": "g"
      },
      {
        "t": "Sterk medianmargin",
        "c": "g"
      }
    ],
    "ai": "Prisen er betydelig under markedsverdi og under privat bucket p25. Marginen er sterk (~42k) og markedsgrunnlaget er solid. Godt kjøp for bilflip.",
    "avgBucketMedianPrivate": null,
    "avgBucketMedianDealer": 359000,
    "avgBucketP25Private": null,
    "avgBucketP75Private": null,
    "avgLowballTarget": 289750,
    "avgLowballMargin": 69250,
    "avgMedianMargin": 54000,
    "avgCompCount": 23,
    "avgCompSpreadPct": 9,
    "bucketCoverage": 0,
    "bucketDealerCoverage": 1,
    "priceToBucketPct": null,
    "underBucketShare": 100,
    "p25DealShare": 0,
    "topCompConfidence": "high",
    "confidenceBreakdown": {
      "high": 1
    },
    "primaryValuationSource": "comps_dealer_min",
    "valuationBreakdown": {
      "comps_dealer_min": 1
    },
    "sellerMix": {
      "unknown": 1
    },
    "analysisBaseCount": 1,
    "cohortFilteredCount": 1,
    "bestDealScore": 52,
    "bestMargin": 34161,
    "faktorer": [
      {
        "l": "Etterspørsel",
        "v": 87,
        "c": "#3d9960"
      },
      {
        "l": "Prismargin",
        "v": 56,
        "c": "#e8a020"
      },
      {
        "l": "Likviditet",
        "v": 15,
        "c": "#e8a020"
      },
      {
        "l": "Batteririsiko",
        "v": 68,
        "c": "#3d9960"
      }
    ]
  },
  {
    "id": "toyotayari",
    "merke": "toyota",
    "navn": "Toyota Yaris Hybrid",
    "sub": "2016–2019 · Active S m/ garanti, ny service, bremser og dekk",
    "score": 41,
    "flipScore": 50,
    "snittPris": 139583,
    "minPris": 120000,
    "maxPris": 159166,
    "snittDager": 21,
    "antallAnnonser": 2,
    "prisEndring": -10247,
    "prisData": [
      227400,
      229416,
      223597,
      224559,
      213676,
      246767,
      217153
    ],
    "volum": [
      2,
      2,
      2,
      2,
      2,
      2,
      2,
      2,
      2,
      2,
      2,
      2
    ],
    "tags": [
      {
        "t": "Lavt volum",
        "c": "a"
      },
      {
        "t": "Pris ned",
        "c": "g"
      },
      {
        "t": "Under bucket",
        "c": "g"
      },
      {
        "t": "Sterk medianmargin",
        "c": "g"
      },
      {
        "t": "Mange under p25",
        "c": "g"
      }
    ],
    "ai": "Toyota Yaris Hybrid — 2 annonser funnet.",
    "avgBucketMedianPrivate": 179677,
    "avgBucketMedianDealer": 154400,
    "avgBucketP25Private": 170355,
    "avgBucketP75Private": 192694,
    "avgLowballTarget": 130810,
    "avgLowballMargin": 48867,
    "avgMedianMargin": 40094,
    "avgCompCount": 8,
    "avgCompSpreadPct": 12,
    "bucketCoverage": 2,
    "bucketDealerCoverage": 2,
    "priceToBucketPct": 78,
    "underBucketShare": 100,
    "p25DealShare": 50,
    "topCompConfidence": "high",
    "confidenceBreakdown": {
      "high": 2
    },
    "primaryValuationSource": "bucket_private_min",
    "valuationBreakdown": {
      "bucket_private_min": 1,
      "bucket_dealer_min": 1
    },
    "sellerMix": {
      "private_likely": 1,
      "unknown": 1
    },
    "analysisBaseCount": 2,
    "cohortFilteredCount": 2,
    "bestDealScore": 60,
    "bestMargin": 6573,
    "faktorer": [
      {
        "l": "Etterspørsel",
        "v": 46,
        "c": "#e8a020"
      },
      {
        "l": "Prismargin",
        "v": 12,
        "c": "#e8a020"
      },
      {
        "l": "Likviditet",
        "v": 30,
        "c": "#e8a020"
      },
      {
        "l": "Batteririsiko",
        "v": 36,
        "c": "#e8a020"
      }
    ]
  },
  {
    "id": "nissanleaf",
    "merke": "nissan",
    "navn": "Nissan Leaf 40kWh",
    "sub": "2021–2020 · Acenta",
    "score": 73,
    "flipScore": 49,
    "snittPris": 139199,
    "minPris": 133532,
    "maxPris": 149532,
    "snittDager": 12,
    "antallAnnonser": 4,
    "prisEndring": -3089,
    "prisData": [
      164195,
      163353,
      162782,
      163869,
      162063,
      121766,
      161106
    ],
    "volum": [
      4,
      4,
      4,
      4,
      4,
      4,
      4,
      4,
      4,
      4,
      4,
      4
    ],
    "tags": [
      {
        "t": "Under bucket",
        "c": "g"
      },
      {
        "t": "Sterk medianmargin",
        "c": "g"
      },
      {
        "t": "Mange under p25",
        "c": "g"
      }
    ],
    "ai": "Privat selger med god beskrivelse, lav km (53k) og 2021-modell. Prisen 153k er under markedsverdi for en slik bil. Ingen kjente feil. God margin mulig.",
    "avgBucketMedianPrivate": 170365,
    "avgBucketMedianDealer": 169000,
    "avgBucketP25Private": 161282,
    "avgBucketP75Private": 175357,
    "avgLowballTarget": 131740,
    "avgLowballMargin": 38625,
    "avgMedianMargin": 31167,
    "avgCompCount": 25,
    "avgCompSpreadPct": 16,
    "bucketCoverage": 3,
    "bucketDealerCoverage": 3,
    "priceToBucketPct": 82,
    "underBucketShare": 100,
    "p25DealShare": 100,
    "topCompConfidence": "high",
    "confidenceBreakdown": {
      "high": 3
    },
    "primaryValuationSource": "comps_private_min",
    "valuationBreakdown": {
      "bucket_dealer_min": 1,
      "comps_private_min": 2
    },
    "sellerMix": {
      "private_likely": 1,
      "unknown": 3
    },
    "analysisBaseCount": 3,
    "cohortFilteredCount": 3,
    "bestDealScore": 63,
    "bestMargin": 5623,
    "faktorer": [
      {
        "l": "Etterspørsel",
        "v": 78,
        "c": "#3d9960"
      },
      {
        "l": "Prismargin",
        "v": 30,
        "c": "#e8a020"
      },
      {
        "l": "Likviditet",
        "v": 60,
        "c": "#1f5fa6"
      },
      {
        "l": "Batteririsiko",
        "v": 52,
        "c": "#e8a020"
      }
    ]
  },
  {
    "id": "nissanleaf",
    "merke": "nissan",
    "navn": "Nissan Leaf Visia,",
    "sub": "2023–2023 · lav km, nybilgaranti, vinterhjul, se pris!",
    "score": 70,
    "flipScore": 48,
    "snittPris": 169900,
    "minPris": 169900,
    "maxPris": 169900,
    "snittDager": 7,
    "antallAnnonser": 1,
    "prisEndring": 0,
    "prisData": [
      169900,
      169900
    ],
    "volum": [
      1,
      1,
      1,
      1,
      1,
      1,
      1,
      1,
      1,
      1,
      1,
      1
    ],
    "tags": [
      {
        "t": "Lavt volum",
        "c": "a"
      },
      {
        "t": "Under bucket",
        "c": "g"
      },
      {
        "t": "Sterk medianmargin",
        "c": "g"
      },
      {
        "t": "Mange under p25",
        "c": "g"
      }
    ],
    "ai": "169 900 kr for en 2023 Leaf Visia med kun 17 500 km er en god pris. Lav km og nybilgaranti øker verdien. Markedsverdi er rundt 195 000 kr, så god margin. Selger er privat, noe som gir rom for forhandling.",
    "avgBucketMedianPrivate": 255253,
    "avgBucketMedianDealer": 199000,
    "avgBucketP25Private": 238879,
    "avgBucketP75Private": 271626,
    "avgLowballTarget": 161405,
    "avgLowballMargin": 93848,
    "avgMedianMargin": 85353,
    "avgCompCount": 24,
    "avgCompSpreadPct": 27,
    "bucketCoverage": 1,
    "bucketDealerCoverage": 1,
    "priceToBucketPct": 67,
    "underBucketShare": 100,
    "p25DealShare": 100,
    "topCompConfidence": "high",
    "confidenceBreakdown": {
      "high": 1
    },
    "primaryValuationSource": "bucket_dealer_min",
    "valuationBreakdown": {
      "bucket_dealer_min": 1
    },
    "sellerMix": {
      "unknown": 1
    },
    "analysisBaseCount": 1,
    "cohortFilteredCount": 1,
    "bestDealScore": 48,
    "bestMargin": 18555,
    "faktorer": [
      {
        "l": "Etterspørsel",
        "v": 75,
        "c": "#3d9960"
      },
      {
        "l": "Prismargin",
        "v": 55,
        "c": "#e8a020"
      },
      {
        "l": "Likviditet",
        "v": 15,
        "c": "#e8a020"
      },
      {
        "l": "Batteririsiko",
        "v": 76,
        "c": "#3d9960"
      }
    ]
  },
  {
    "id": "toyotayari",
    "merke": "toyota",
    "navn": "Toyota Yaris 1,5",
    "sub": "2022–2024 · Hybrid Active Tech",
    "score": 78,
    "flipScore": 44,
    "snittPris": 233950,
    "minPris": 199900,
    "maxPris": 268000,
    "snittDager": 9,
    "antallAnnonser": 3,
    "prisEndring": -270,
    "prisData": [
      267543,
      266056,
      265352,
      265985,
      266433,
      143378,
      267273
    ],
    "volum": [
      3,
      3,
      3,
      3,
      3,
      3,
      3,
      3,
      3,
      3,
      3,
      3
    ],
    "tags": [
      {
        "t": "Over bucket",
        "c": "a"
      },
      {
        "t": "Mange under p25",
        "c": "g"
      }
    ],
    "ai": "Svært attraktiv bil med lav km for årsmodell, service inkludert til 2027. Toyota Yaris Hybrid er etterspurt og holder verdien godt. Prisen er konkurransedyktig for en 2022-modell.",
    "avgBucketMedianPrivate": 222236,
    "avgBucketMedianDealer": 278750,
    "avgBucketP25Private": 222236,
    "avgBucketP75Private": 222236,
    "avgLowballTarget": 219754,
    "avgLowballMargin": 35865,
    "avgMedianMargin": 21668,
    "avgCompCount": 18,
    "avgCompSpreadPct": 12,
    "bucketCoverage": 1,
    "bucketDealerCoverage": 2,
    "priceToBucketPct": 105,
    "underBucketShare": 100,
    "p25DealShare": 50,
    "topCompConfidence": "high",
    "confidenceBreakdown": {
      "high": 2
    },
    "primaryValuationSource": "bucket_private_min",
    "valuationBreakdown": {
      "bucket_private_min": 1,
      "bucket_dealer_min": 1
    },
    "sellerMix": {
      "unknown": 3
    },
    "analysisBaseCount": 2,
    "cohortFilteredCount": 2,
    "bestDealScore": 52,
    "bestMargin": 11771,
    "faktorer": [
      {
        "l": "Etterspørsel",
        "v": 83,
        "c": "#3d9960"
      },
      {
        "l": "Prismargin",
        "v": 27,
        "c": "#e8a020"
      },
      {
        "l": "Likviditet",
        "v": 45,
        "c": "#e8a020"
      },
      {
        "l": "Batteririsiko",
        "v": 68,
        "c": "#3d9960"
      }
    ]
  },
  {
    "id": "nissanleaf",
    "merke": "nissan",
    "navn": "Nissan Leaf Nordic",
    "sub": "2015–2015 · Diverse",
    "score": 0,
    "flipScore": 41,
    "snittPris": 27532,
    "minPris": 27532,
    "maxPris": 27532,
    "snittDager": 2,
    "antallAnnonser": 1,
    "prisEndring": -11358,
    "prisData": [
      62516,
      62516,
      74000,
      74000,
      62971,
      27532,
      51158
    ],
    "volum": [
      1,
      1,
      1,
      1,
      1,
      1,
      1,
      1,
      1,
      1,
      1,
      1
    ],
    "tags": [
      {
        "t": "God margin",
        "c": "g"
      },
      {
        "t": "Lavt volum",
        "c": "a"
      },
      {
        "t": "Pris ned",
        "c": "g"
      },
      {
        "t": "Under bucket",
        "c": "g"
      },
      {
        "t": "Sterk medianmargin",
        "c": "g"
      },
      {
        "t": "Mange under p25",
        "c": "g"
      }
    ],
    "ai": "Nissan Leaf Nordic — 1 annonser funnet.",
    "avgBucketMedianPrivate": 99032,
    "avgBucketMedianDealer": 56942,
    "avgBucketP25Private": 99032,
    "avgBucketP75Private": 99032,
    "avgLowballTarget": 25880,
    "avgLowballMargin": 73152,
    "avgMedianMargin": 71500,
    "avgCompCount": 0,
    "avgCompSpreadPct": null,
    "bucketCoverage": 1,
    "bucketDealerCoverage": 1,
    "priceToBucketPct": 28,
    "underBucketShare": 100,
    "p25DealShare": 100,
    "topCompConfidence": "low",
    "confidenceBreakdown": {
      "low": 1
    },
    "primaryValuationSource": "bucket_private",
    "valuationBreakdown": {
      "bucket_private": 1
    },
    "sellerMix": {
      "unknown": 1
    },
    "analysisBaseCount": 1,
    "cohortFilteredCount": 0,
    "bestDealScore": 41,
    "bestMargin": 63955,
    "faktorer": [
      {
        "l": "Etterspørsel",
        "v": 5,
        "c": "#e8a020"
      },
      {
        "l": "Prismargin",
        "v": 100,
        "c": "#3d9960"
      },
      {
        "l": "Likviditet",
        "v": 15,
        "c": "#e8a020"
      },
      {
        "l": "Batteririsiko",
        "v": 20,
        "c": "#e8a020"
      }
    ]
  },
  {
    "id": "volkswagen",
    "merke": "volkswagen",
    "navn": "Volkswagen Golf-Serie 2020",
    "sub": "2020–2020 · ∙ 57 000 km ∙ El ∙ 229 km rekkevidde",
    "score": 85,
    "flipScore": 40,
    "snittPris": 139532,
    "minPris": 139532,
    "maxPris": 139532,
    "snittDager": 22,
    "antallAnnonser": 1,
    "prisEndring": -1634,
    "prisData": [
      139322,
      152322,
      155688,
      152355,
      137688,
      137688
    ],
    "volum": [
      1,
      1,
      1,
      1,
      1,
      1,
      1,
      1,
      1,
      1,
      1,
      1
    ],
    "tags": [
      {
        "t": "God margin",
        "c": "g"
      },
      {
        "t": "Lavt volum",
        "c": "a"
      },
      {
        "t": "Høy score",
        "c": "g"
      }
    ],
    "ai": "Svært godt kjøp fra privatperson. Lav km for årsmodell, full Møller-service og mobilitetsgaranti. Ingen kjente feil. Prisen er 30-40k under markedsverdi for en tilsvarende Golf elbil hos forhandler.",
    "avgBucketMedianPrivate": null,
    "avgBucketMedianDealer": 129000,
    "avgBucketP25Private": null,
    "avgBucketP75Private": null,
    "avgLowballTarget": 131160,
    "avgLowballMargin": -2160,
    "avgMedianMargin": -10532,
    "avgCompCount": 1,
    "avgCompSpreadPct": 0,
    "bucketCoverage": 0,
    "bucketDealerCoverage": 1,
    "priceToBucketPct": null,
    "underBucketShare": 0,
    "p25DealShare": 0,
    "topCompConfidence": "low",
    "confidenceBreakdown": {
      "low": 1
    },
    "primaryValuationSource": "ai_fallback",
    "valuationBreakdown": {
      "ai_fallback": 1
    },
    "sellerMix": {
      "private_likely": 1
    },
    "analysisBaseCount": 1,
    "cohortFilteredCount": 0,
    "bestDealScore": 40,
    "bestMargin": 31923,
    "faktorer": [
      {
        "l": "Etterspørsel",
        "v": 90,
        "c": "#3d9960"
      },
      {
        "l": "Prismargin",
        "v": 100,
        "c": "#3d9960"
      },
      {
        "l": "Likviditet",
        "v": 15,
        "c": "#e8a020"
      },
      {
        "l": "Batteririsiko",
        "v": 52,
        "c": "#e8a020"
      }
    ]
  },
  {
    "id": "volkswagen",
    "merke": "volkswagen",
    "navn": "Volkswagen Golf-Serie e‑Golf",
    "sub": "2020–2020 · Exclusive - fullspekket topputgave I EU til 2028",
    "score": 70,
    "flipScore": 40,
    "snittPris": 159900,
    "minPris": 159900,
    "maxPris": 159900,
    "snittDager": 7,
    "antallAnnonser": 1,
    "prisEndring": 0,
    "prisData": [
      159900
    ],
    "volum": [
      1,
      1,
      1,
      1,
      1,
      1,
      1,
      1,
      1,
      1,
      1,
      1
    ],
    "tags": [
      {
        "t": "Lavt volum",
        "c": "a"
      }
    ],
    "ai": "2020 e-Golf Exclusive til 159 900 kr med 66 300 km. Fullspekket topputgave med EU til 2028. Markedspris for tilsvarende er 170 000–185 000 kr. God margin på 10 000–20 000 kr. Lav risiko.",
    "avgBucketMedianPrivate": null,
    "avgBucketMedianDealer": null,
    "avgBucketP25Private": null,
    "avgBucketP75Private": null,
    "avgLowballTarget": 151905,
    "avgLowballMargin": -151905,
    "avgMedianMargin": null,
    "avgCompCount": 0,
    "avgCompSpreadPct": null,
    "bucketCoverage": 0,
    "bucketDealerCoverage": 0,
    "priceToBucketPct": null,
    "underBucketShare": 0,
    "p25DealShare": 0,
    "topCompConfidence": "low",
    "confidenceBreakdown": {
      "low": 1
    },
    "primaryValuationSource": "ai_fallback",
    "valuationBreakdown": {
      "ai_fallback": 1
    },
    "sellerMix": {
      "private_likely": 1
    },
    "analysisBaseCount": 1,
    "cohortFilteredCount": 0,
    "bestDealScore": 40,
    "bestMargin": 12555,
    "faktorer": [
      {
        "l": "Etterspørsel",
        "v": 75,
        "c": "#3d9960"
      },
      {
        "l": "Prismargin",
        "v": 39,
        "c": "#e8a020"
      },
      {
        "l": "Likviditet",
        "v": 15,
        "c": "#e8a020"
      },
      {
        "l": "Batteririsiko",
        "v": 52,
        "c": "#e8a020"
      }
    ]
  },
  {
    "id": "volkswagen",
    "merke": "volkswagen",
    "navn": "Volkswagen ID.4 2021",
    "sub": "2021–2021 · ∙ 43 500 km ∙ El ∙ 495 km rekkevidde",
    "score": 80,
    "flipScore": 37,
    "snittPris": 239000,
    "minPris": 239000,
    "maxPris": 239000,
    "snittDager": 34,
    "antallAnnonser": 1,
    "prisEndring": 0,
    "prisData": [
      239000
    ],
    "volum": [
      1,
      1,
      1,
      1,
      1,
      1,
      1,
      1,
      1,
      1,
      1,
      1
    ],
    "tags": [
      {
        "t": "Lavt volum",
        "c": "a"
      },
      {
        "t": "Høy score",
        "c": "g"
      },
      {
        "t": "Under bucket",
        "c": "g"
      }
    ],
    "ai": "Volkswagen ID.4 2021 med bare 43 500 km til 239 000 kr. Dette er en svært god pris for en populær el-SUV med lav km. Privatsalg, ingen større reparasjoner. Stor potensiell margin.",
    "avgBucketMedianPrivate": 259483,
    "avgBucketMedianDealer": 279450,
    "avgBucketP25Private": 236959,
    "avgBucketP75Private": 282008,
    "avgLowballTarget": 224660,
    "avgLowballMargin": 34823,
    "avgMedianMargin": 20483,
    "avgCompCount": 7,
    "avgCompSpreadPct": 14,
    "bucketCoverage": 1,
    "bucketDealerCoverage": 1,
    "priceToBucketPct": 92,
    "underBucketShare": 100,
    "p25DealShare": 0,
    "topCompConfidence": "high",
    "confidenceBreakdown": {
      "high": 1
    },
    "primaryValuationSource": "bucket_private_min",
    "valuationBreakdown": {
      "bucket_private_min": 1
    },
    "sellerMix": {
      "unknown": 1
    },
    "analysisBaseCount": 1,
    "cohortFilteredCount": 1,
    "bestDealScore": 37,
    "bestMargin": 6918,
    "faktorer": [
      {
        "l": "Etterspørsel",
        "v": 85,
        "c": "#3d9960"
      },
      {
        "l": "Prismargin",
        "v": 14,
        "c": "#e8a020"
      },
      {
        "l": "Likviditet",
        "v": 15,
        "c": "#e8a020"
      },
      {
        "l": "Batteririsiko",
        "v": 60,
        "c": "#3d9960"
      }
    ]
  },
  {
    "id": "hyundaikon",
    "merke": "hyundai",
    "navn": "Hyundai Kona 2022",
    "sub": "2022–2022 · ∙ 57 000 km ∙ El ∙ 355 km rekkevidde",
    "score": 80,
    "flipScore": 37,
    "snittPris": 182500,
    "minPris": 182500,
    "maxPris": 182500,
    "snittDager": 17,
    "antallAnnonser": 1,
    "prisEndring": -8700,
    "prisData": [
      199900,
      199900,
      190950,
      205950,
      191200,
      191200
    ],
    "volum": [
      1,
      1,
      1,
      1,
      1,
      1,
      1,
      1,
      1,
      1,
      1,
      1
    ],
    "tags": [
      {
        "t": "Lavt volum",
        "c": "a"
      },
      {
        "t": "Høy score",
        "c": "g"
      },
      {
        "t": "Pris ned",
        "c": "g"
      }
    ],
    "ai": "2022 Kona med 57 000 km til 182 000 kr fra privat. Meget god pris - tilsvarende selges for 210-230 000 kr hos forhandler. Beste flip-muligheten i listen.",
    "avgBucketMedianPrivate": null,
    "avgBucketMedianDealer": 199900,
    "avgBucketP25Private": null,
    "avgBucketP75Private": null,
    "avgLowballTarget": 173375,
    "avgLowballMargin": 26525,
    "avgMedianMargin": 17400,
    "avgCompCount": 1,
    "avgCompSpreadPct": 0,
    "bucketCoverage": 0,
    "bucketDealerCoverage": 1,
    "priceToBucketPct": null,
    "underBucketShare": 100,
    "p25DealShare": 0,
    "topCompConfidence": "low",
    "confidenceBreakdown": {
      "low": 1
    },
    "primaryValuationSource": "ai_fallback",
    "valuationBreakdown": {
      "ai_fallback": 1
    },
    "sellerMix": {
      "private_likely": 1
    },
    "analysisBaseCount": 1,
    "cohortFilteredCount": 0,
    "bestDealScore": 37,
    "bestMargin": 18935,
    "faktorer": [
      {
        "l": "Etterspørsel",
        "v": 85,
        "c": "#3d9960"
      },
      {
        "l": "Prismargin",
        "v": 52,
        "c": "#e8a020"
      },
      {
        "l": "Likviditet",
        "v": 15,
        "c": "#e8a020"
      },
      {
        "l": "Batteririsiko",
        "v": 68,
        "c": "#3d9960"
      }
    ]
  }
]